{"Verses":{"1":{"_id":1,"VerseHTML":"<p class=\"q1\"><sup id=\"Ps.23.1\" class=\"v\">1</sup>The L<span class=\"sc\">ORD</span> is my shepherd,</p>\n<p class=\"q2\">I shall not want.</p>"},"2":{"_id":2,"VerseHTML":"<p class=\"q1\"><sup id=\"Ps.23.2\" class=\"v\">2</sup>He makes me lie down in green pastures;</p>\n<p class=\"q2\">He leads me beside quiet waters.</p>"},"3":{"_id":3,"VerseHTML":"<p class=\"q1\"><sup id=\"Ps.23.3\" class=\"v\">3</sup>He restores my soul;</p>\n<p class=\"q2\">He guides me in the paths of righteousness</p>\n<p class=\"q2\">For His name’s sake.</p>\n<p class=\"b\"></p>"},"4":{"_id":4,"VerseHTML":"<p class=\"q1\"><sup id=\"Ps.23.4\" class=\"v\">4</sup>Even though I walk through the valley of the shadow of death,</p>\n<p class=\"q2\">I fear no evil, for You are with me;</p>\n<p class=\"q2\">Your rod and Your staff, they comfort me.</p>"},"5":{"_id":5,"VerseHTML":"<p class=\"q1\"><sup id=\"Ps.23.5\" class=\"v\">5</sup>You prepare a table before me in the presence of my enemies;</p>\n<p class=\"q2\">You have anointed my head with oil;</p>\n<p class=\"q2\">My cup overflows.</p>"},"6":{"_id":6,"VerseHTML":"<p class=\"q1\"><sup id=\"Ps.23.6\" class=\"v\">6</sup>Surely goodness and lovingkindness will follow me all the days of my life,</p>\n<p class=\"q2\">And I will dwell in the house of the L<span class=\"sc\">ORD</span> forever.</p>"}}}